LICENSE
databricks_sdk_python/__init__.py
databricks_sdk_python/api_client/__init__.py
databricks_sdk_python/api_client/account/__init__.py
databricks_sdk_python/api_client/account/aws/__init__.py
databricks_sdk_python/api_client/account/aws/client.py
databricks_sdk_python/api_client/account/aws/credentials.py
databricks_sdk_python/api_client/account/aws/networks.py
databricks_sdk_python/api_client/account/aws/storage_configuration.py
databricks_sdk_python/api_client/account/aws/workspaces.py
databricks_sdk_python/api_client/client.py
databricks_sdk_python/api_client/utils.py
databricks_sdk_python/api_client/workspace/__init__.py
databricks_sdk_python/api_client/workspace/client.py
databricks_sdk_python/api_client/workspace/instance_profiles.py
databricks_sdk_python/api_client/workspace/permissions.py
databricks_sdk_python/api_client/workspace/unity_catalog/__init__.py
databricks_sdk_python/api_client/workspace/unity_catalog/catalogs.py
databricks_sdk_python/api_client/workspace/unity_catalog/client.py
databricks_sdk_python/api_client/workspace/unity_catalog/metastores.py
databricks_sdk_python/api_client/workspace/unity_catalog/schemas.py
databricks_sdk_python/resources/__init__.py
databricks_sdk_python/resources/account/__init__.py
databricks_sdk_python/resources/account/aws/__init__.py
databricks_sdk_python/resources/account/aws/credentials.py
databricks_sdk_python/resources/account/aws/networks.py
databricks_sdk_python/resources/account/aws/storage_config.py
databricks_sdk_python/resources/account/aws/workspaces.py
databricks_sdk_python/resources/base.py
databricks_sdk_python/resources/workspace/__init__.py
databricks_sdk_python/resources/workspace/instance_profiles.py
databricks_sdk_python/resources/workspace/permissions.py
databricks_sdk_python/resources/workspace/unity_catalog/__init__.py
databricks_sdk_python/resources/workspace/unity_catalog/catalogs.py
databricks_sdk_python/resources/workspace/unity_catalog/metastores.py
databricks_sdk_python-0.0.3.dist-info/LICENSE
databricks_sdk_python-0.0.3.dist-info/WHEEL
databricks_sdk_python-0.0.3.dist-info/METADATA
databricks_sdk_python-0.0.3.dist-info/RECORD
